<?xml version="1.0" encoding="utf-8" ?>
<Defs>
    <FactionDef>
        <defName>WNA_FactionWNA</defName>
        <label>Whellingnorther Alliance</label>
        <categoryTag>WNA_FactionWNA</categoryTag>
        <factionIconPath>factions/wna_alliance</factionIconPath>
        <settlementTexturePath>karma</settlementTexturePath>
        <description>Thousands of years ago they rose from a remote planet where people suffers from conflicts and oppression, since then they have spread their activities across the known universe, mysterious as ghosts and omnipresent as shades. These black-hooded figure and the Whelingnorther Humanoid Revolt under their command have brought death and horror to almost everywhere they reached. This cult itself is relatively young but actually their origin is far more ancient, even older than the universe.\n\nThis branch of Whelingnorther Alliance have settled on this rimworld for a long time. Although they appear to be peaceful at the moment, they have undoubtedly had plenty of violent conflicts with other factions on the planet. Recently they seem to be becoming active again and preparing to achieve their ultimate goal - the Whelingnorther Apocalypse.</description>
        <pawnSingular>follower</pawnSingular>
        <pawnsPlural>followers</pawnsPlural>
        <listOrderPriority>1</listOrderPriority>
        <maxConfigurableAtWorldCreation>1</maxConfigurableAtWorldCreation>
        <configurationListOrderPriority>1</configurationListOrderPriority>
        <settlementGenerationWeight>1</settlementGenerationWeight>
        <requiredCountAtGameStart>1</requiredCountAtGameStart>
        <maxCountAtGameStart>1</maxCountAtGameStart>
        <canMakeRandomly>false</canMakeRandomly>
        <canSiege>false</canSiege>
        <canStageAttacks>false</canStageAttacks>
        <leaderTitle>saint</leaderTitle>
        <fixedName>Whellingnorther Alliance</fixedName>
        <settlementNameMaker>WNA_NamerSettlement</settlementNameMaker>
        <techLevel>Archotech</techLevel>
        <autoFlee>false</autoFlee>
        <canRequestTraders>false</canRequestTraders>
        <canRequestOrbitalTrader>true</canRequestOrbitalTrader>
        <layerBlacklist/>
        <arrivalLayerBlacklist/>
        <colorSpectrum> <li>(0,0,0)</li> </colorSpectrum>
        <permanentEnemyToEveryoneExceptPlayer>true</permanentEnemyToEveryoneExceptPlayer>
        <hostileToFactionlessHumanlikes>true</hostileToFactionlessHumanlikes>
        <hidden>false</hidden>
        <allowedCultures>
            <li>WNA_WhelingnortherCulture</li>
        </allowedCultures>
        <apparelStuffFilter>
            <thingDefs>
                <li>WNA_AttunementFabric</li>
                <li>WNA_DarkAsbestos</li>
            </thingDefs>
        </apparelStuffFilter>
        <backstoryFilters>
            <li>
                <categories>
                    <li>WNA_Backstory_Norm</li>
                </categories>
                <commonality>0.8</commonality>
            </li>
            <li>
                <categories>
                    <li>WNA_Backstory_Uplifted</li>
                </categories>
                <commonality>0.2</commonality>
            </li>
        </backstoryFilters>
        <caravanTraderKinds/>
        <visitorTraderKinds/>
        <orbitalTraderKinds>
            <li>WNA_Trader_Orbital</li>
        </orbitalTraderKinds>
        <baseTraderKinds>
            <li>WNA_Trader_Settlement</li>
        </baseTraderKinds>
        <allowedArrivalTemperatureRange>-2000~2000</allowedArrivalTemperatureRange>
        <raidLootMaker>WNA_FollowerRaidLootMaker</raidLootMaker>
        <raidLootValueFromPointsCurve>
            <points>
                <li>(35,0)</li>
                <li>(100,0)</li>
                <li>(1000,0)</li>
                <li>(2000,0)</li>
                <li>(4000,0)</li>
                <li>(10000,0)</li>
            </points>
        </raidLootValueFromPointsCurve>
        <maxPawnCostPerTotalPointsCurve>
            <points>
                <li>(0,35)</li>
                <li>(70,70)</li>
                <li>(700,700)</li>
                <li>(1300,1300)</li>
                <li>(10000,10000)</li>
            </points>
        </maxPawnCostPerTotalPointsCurve>
        <pawnGroupMakers>
            <li>
                <kindDef>Settlement</kindDef>
                <options>
                    <WNA_IronGuard>50</WNA_IronGuard>
                    <WNA_Vanguard>50</WNA_Vanguard>
                    <WNA_Disciple>50</WNA_Disciple>
                    <WNA_DarknightComm>30</WNA_DarknightComm>
                    <WNA_Saint>1</WNA_Saint>
                </options>
            </li>
            <li>
                <kindDef>Combat</kindDef>
                <commonality>200</commonality>
                <options>
                    <WNA_FieldTroop>20</WNA_FieldTroop>
                </options>
            </li>
            <li>
                <kindDef>Combat</kindDef>
                <commonality>200</commonality>
                <options>
                    <WNA_FieldTroop>20</WNA_FieldTroop>
                    <WNA_StrikeForce>20</WNA_StrikeForce>
                    <WNA_Vanguard>20</WNA_Vanguard>
                    <WNA_DarknightComm>10</WNA_DarknightComm>
                </options>
            </li>
            <li>
                <kindDef>Combat</kindDef>
                <commonality>100</commonality>
                <options>
                    <WNA_StrikeForce>20</WNA_StrikeForce>
                    <WNA_DarknightComm>20</WNA_DarknightComm>
                    <WNA_Vanguard>40</WNA_Vanguard>
                </options>
            </li>
            <li>
                <kindDef>Combat</kindDef>
                <commonality>100</commonality>
                <options>
                    <WNA_FieldTroop>20</WNA_FieldTroop>
                    <WNA_StrikeForce>20</WNA_StrikeForce>
                    <WNA_Vanguard>20</WNA_Vanguard>
                    <WNA_DarknightComm>20</WNA_DarknightComm>
                    <WNA_Disciple>20</WNA_Disciple>
                </options>
            </li>
            <li>
                <kindDef>Combat</kindDef>
                <commonality>100</commonality>
                <options>
                    <WNA_Disciple>20</WNA_Disciple>
                    <WNA_DimBoo>15</WNA_DimBoo>
                    <WNA_ThornBoo>15</WNA_ThornBoo>
                </options>
            </li>
            <li>
                <kindDef>Combat</kindDef>
                <commonality>5</commonality>
                <options>
                    <WNA_Disciple>20</WNA_Disciple>
                    <WNA_Saint>1</WNA_Saint>
                </options>
            </li>
            <li>
                <kindDef>Peaceful</kindDef>
                <options>
                    <WNA_Technician>5</WNA_Technician>
                    <WNA_FieldTroop>5</WNA_FieldTroop>
                    <WNA_StrikeForce>5</WNA_StrikeForce>
                    <WNA_DarknightComm>3</WNA_DarknightComm>
                    <WNA_Disciple>3</WNA_Disciple>
                </options>
            </li>
        </pawnGroupMakers>
        <dropPodIncoming>WNA_WARPIN</dropPodIncoming>
        <dropPodActive>WNA_WARPON</dropPodActive>
        <fixedIdeo MayRequire="Ludeon.Rimworld.Ideology">true</fixedIdeo>
        <hiddenIdeo MayRequire="Ludeon.Rimworld.Ideology">true</hiddenIdeo>
        <ideoName MayRequire="Ludeon.Rimworld.Ideology">Whelingnorther Holyorder</ideoName>
        <ideoDescription MayRequire="Ludeon.Rimworld.Ideology">When the ancient whelingnorthans faced calamity and annihilation, it was their effort and sacrifice that led to the greatness and glory of Whelingnorther Empire; when the ancestors of us rise from the humble, it was their effort and sacrifices that led to we Whelingnorther Alliance. No great works can be done without great sacrifices, without great devotions we cannot achieve eternity, salvation and immortality. We descendants will follow the path led by those who came before us; we will understand our duty and accept our manifest destiny; we shall alter and determine the past, the present and the future. Every corner of existance shall bath in the glory of Whelignorther, they may not understand, but they shall obey and follow.</ideoDescription>
        <modExtensions/>
    </FactionDef>

    <ThingSetMakerDef>
        <defName>WNA_FollowerRaidLootMaker</defName>
        <root Class="ThingSetMaker_MarketValue">
            <fixedParams>
                <filter>
                    <thingDefs>
                        <li>WNA_Ration</li>
                        <li>WNA_Medikit</li>
                    </thingDefs>
                </filter>
            </fixedParams>
        </root>
    </ThingSetMakerDef>

    <RulePackDef>
        <defName>WNA_NamerSettlement</defName>
        <rulePack>
            <rulesStrings>
                <li>r_name->[pfix] [Digit][Digit][Digit]</li>
                <li>r_name->[pfix] [Digit][Digit][Digit][Digit]</li>
                <li>r_name->[Digit][Digit][Digit]th [pfix]</li>
                <li>r_name->[Digit][Digit][Digit][Digit]th [pfix]</li>
                <!---->
                <li>pfix->Facility</li>
                <li>pfix->Outpost</li>
                <li>pfix->Site</li>
                <li>pfix(p=4)->Field Task</li>
                <!---->
                <li>r_name(p=0.01)->Celestial Throne</li>
                <li>r_name(p=0.01)->Sky Temple</li>
                <li>r_name(p=0.01)->Pristine Jewel</li>
                <li>r_name(p=0.01)->Emerald Mausoleum</li>
                <li>r_name(p=0.01)->Walled Garden</li>
                <li>r_name(p=0.01)->Prophet's Retreat</li>
                <li>r_name(p=0.01)->The Cradle</li>
                <li>r_name(p=0.01)->The Preserve</li>
                <li>r_name(p=0.01)->Font of Knowledge</li>
                <li>r_name(p=0.01)->The Archives</li>
                <li>r_name(p=0.01)->Last Thought</li>
                <li>r_name(p=0.01)->Ithome's Gate</li>
                <li>r_name(p=0.01)->Looks to the Moon</li>
                <li>r_name(p=0.01)->Five Pebbles</li>
                <li>r_name(p=0.01)->Outer Expanse</li>
                <li>r_name(p=0.01)->Outer Rim</li>
                <li>r_name(p=0.01)->Memory Crypts</li>
                <li>r_name(p=0.01)->Rubicon</li>
                <li>r_name(p=0.01)->Aether Ridge</li>
                <li>r_name(p=0.01)->Daemon</li>
                <li>r_name(p=0.01)->Shattered Terrace</li>
                <li>r_name(p=0.01)->Ancient Urban</li>
                <li>r_name(p=0.01)->Station Annex</li>
                <li>r_name(p=0.01)->Unfortunate Evolution</li>
            </rulesStrings>
        </rulePack>
    </RulePackDef>
    
    <RulePackDef>
        <defName>WNA_NamerPawn</defName>
        <rulePack>
            <rulesStrings>
                <li>r_name(p=2)->[postfx] [prefix]</li>
                <li>r_name->[ImperialNameFirstMale] [ImperialNameLast]</li>
                <li>r_name->[randName] [ImperialNameLast]</li>
                <li>r_name(p=0.1)->[codeName] [codeName]</li>
                <!---->
                <li>randName(p=2)->[SylB][SylB][SylB]</li>
                <li>randName->[SylB][SylB][SylB][SylB]</li>
                <li>codeName->[pre]-[pos]</li>
                <li>pre(p=3)->[code][code][code]</li>
                <li>pre->[code][code][code][code]</li>
                <li>pos(p=3)->[code][code][code]</li>
                <li>pos->[code][code][code][code]</li>
                <!---->
                <li>code->[Digit]</li>
                <li>code->[Letter]</li>
            </rulesStrings>
            <rulesFiles>
                <li>ImperialNameFirstMale->Names/Imperial_First_Male</li>
                <li>ImperialNameLast->Names/Imperial_Last</li>
                <li>prefix->Names/wna_name</li>
                <li>postfx->Names/wna_family</li>
            </rulesFiles>
        </rulePack>
    </RulePackDef>
    
    <RulePackDef>
        <defName>WNA_NamerPawnW</defName>
        <rulePack>
            <rulesStrings>
                <li>r_name->[postfx] [prefix]</li>
                <li>r_name(p=0.035714)->[pos1] [pre1]</li>
                <li>r_name(p=0.035714)->[pos2] [pre2]</li>
                <li>r_name(p=0.035714)->[pos3] [pre3]</li>
                <li>r_name(p=0.035714)->[pos4] [pre4]</li>
                <li>r_name(p=0.035714)->[pos5] [pre5]</li>
                <li>r_name(p=0.035714)->[pos6] [pre6]</li>
                <li>r_name(p=0.035714)->[pos7] [pre7]</li>
                <li>r_name(p=0.035714)->[pos8] [pre8]</li>
                <li>r_name(p=0.035714)->[pos9] [pre9]</li>
                <li>r_name(p=0.035714)->[pos10] [pre10]</li>
                <li>r_name(p=0.035714)->[pos11] [pre11]</li>
                <li>r_name(p=0.035714)->[pos12] [pre12]</li>
                <li>r_name(p=0.035714)->[pos13] [pre13]</li>
                <li>r_name(p=0.035714)->[pos14] [pre14]</li>
                <li>r_name(p=0.035714)->[pos15] [pre15]</li>
                <li>r_name(p=0.035714)->[pos16] [pre16]</li>
                <li>r_name(p=0.035714)->[pos17] [pre17]</li>
                <li>r_name(p=0.035714)->[pos18] [pre18]</li>
                <li>r_name(p=0.035714)->[pos19] [pre19]</li>
                <li>r_name(p=0.035714)->[pos20] [pre20]</li>
                <li>r_name(p=0.035714)->[pos21] [pre21]</li>
                <li>r_name(p=0.035714)->[pos22] [pre22]</li>
                <li>r_name(p=0.035714)->[pos23] [pre23]</li>
                <li>r_name(p=0.035714)->[pos24] [pre24]</li>
                <li>r_name(p=0.035714)->[pos25] [pre25]</li>
                <li>r_name(p=0.035714)->[pos26] [pre26]</li>
                <li>r_name(p=0.035714)->[pos27] [pre27]</li>
                <li>r_name(p=0.035714)->[pos28] [pre28]</li>
                <!-- special fixed -->
                <li>pos1->角</li><li>pre1->木蛟</li>
                <li>pos2->亢</li><li>pre2->金龙</li>
                <li>pos3->氐</li><li>pre3->土貉</li>
                <li>pos4->房</li><li>pre4->日兔</li>
                <li>pos5->心</li><li>pre5->月狐</li>
                <li>pos6->尾</li><li>pre6->火虎</li>
                <li>pos7->箕</li><li>pre7->水豹</li>
                <li>pos8->斗</li><li>pre8->木獬</li>
                <li>pos9->牛</li><li>pre9->金牛</li>
                <li>pos10->女</li><li>pre10->土蝠</li>
                <li>pos11->虚</li><li>pre11->日鼠</li>
                <li>pos12->危</li><li>pre12->月燕</li>
                <li>pos13->室</li><li>pre13->火猪</li>
                <li>pos14->壁</li><li>pre14->水貐</li>
                <li>pos15->奎</li><li>pre15->木狼</li>
                <li>pos16->娄</li><li>pre16->金狗</li>
                <li>pos17->胃</li><li>pre17->土雉</li>
                <li>pos18->昴</li><li>pre18->日鸡</li>
                <li>pos19->毕</li><li>pre19->月乌</li>
                <li>pos20->觜</li><li>pre20->火猴</li>
                <li>pos21->参</li><li>pre21->水猿</li>
                <li>pos22->井</li><li>pre22->木犴</li>
                <li>pos23->鬼</li><li>pre23->金羊</li>
                <li>pos24->柳</li><li>pre24->土獐</li>
                <li>pos25->星</li><li>pre25->日马</li>
                <li>pos26->张</li><li>pre26->月鹿</li>
                <li>pos27->翼</li><li>pre27->火蛇</li>
                <li>pos28->轸</li><li>pre28->水蚓</li>
            </rulesStrings>
            <rulesFiles>
                <li>prefix->Names/wna_name</li>
                <li>postfx->Names/wna_family</li>
            </rulesFiles>
        </rulePack>
    </RulePackDef>
    
</Defs>
